image_upscaling_api-2025.0.12.dist-info/METADATA
image_upscaling_api-2025.0.12.dist-info/WHEEL
image_upscaling_api-2025.0.12.dist-info/entry_points.txt
image_upscaling_api/__init__.py
image_upscaling_api-2025.0.12.dist-info/RECORD
