Metadata-Version: 2.1
Name: image_upscaling_api
Version: 2025.0.12
Summary: image-upscaling.net api client
Keywords: upscale,image upscale,ai,image-processing,image-upscaling,super-resolution,machine-learning,deep-learning,api,free
Author: Marvin Eckhardt
Maintainer: Marvin Eckhardt
Classifier: Programming Language :: Python
Classifier: License :: OSI Approved :: MIT License
Classifier: Topic :: Scientific/Engineering :: Image Processing
Project-URL: Homepage, https://image-upscaling.net
Requires-Python: >=3
Requires-Dist: requests
